indianconstitution/__init__.py
indianconstitution/cli.py
indianconstitution/constitution_of_india.json
indianconstitution/indianconstitution.py
indianconstitution-1.0.1.dist-info/licenses/LICENSE
indianconstitution-1.0.1.dist-info/METADATA
indianconstitution-1.0.1.dist-info/WHEEL
indianconstitution-1.0.1.dist-info/entry_points.txt
indianconstitution-1.0.1.dist-info/top_level.txt
indianconstitution-1.0.1.dist-info/RECORD
