Metadata-Version: 2.4
Name: IndianConstitution
Version: 1.0.1
Summary: AI- and NLP-enabled Python framework for programmatic access, analysis, and research on the Constitution of India.
Home-page: https://github.com/Vikhram-S/IndianConstitution
Author: Vikhram S
Author-email: vikhrams@saveetha.ac.in
Maintainer: Vikhram S
Maintainer-email: vikhrams@saveetha.ac.in
License: Apache License 2.0
Project-URL: Documentation, https://pypi.org/project/IndianConstitution/
Project-URL: Source, https://github.com/Vikhram-S/IndianConstitution
Project-URL: Issue Tracker, https://github.com/Vikhram-S/IndianConstitution/issues
Project-URL: Changelog, https://github.com/Vikhram-S/IndianConstitution/blob/main/changelog.md
Keywords: constitution of india,legaltech,civic tech,india ai,nlp,ai,law,policy research,open data,constitutional law
Classifier: Development Status :: 5 - Production/Stable
Classifier: Intended Audience :: Developers
Classifier: Intended Audience :: Education
Classifier: Intended Audience :: Legal Industry
Classifier: Intended Audience :: Science/Research
Classifier: License :: OSI Approved :: Apache Software License
Classifier: Natural Language :: English
Classifier: Operating System :: OS Independent
Classifier: Programming Language :: Python
Classifier: Programming Language :: Python :: 3
Classifier: Programming Language :: Python :: 3.7
Classifier: Programming Language :: Python :: 3.8
Classifier: Programming Language :: Python :: 3.9
Classifier: Programming Language :: Python :: 3.10
Classifier: Programming Language :: Python :: 3.11
Classifier: Programming Language :: Python :: 3.12
Classifier: Topic :: Software Development :: Libraries
Classifier: Topic :: Software Development :: Libraries :: Python Modules
Classifier: Topic :: Scientific/Engineering :: Artificial Intelligence
Classifier: Topic :: Text Processing :: Linguistic
Classifier: Topic :: Sociology
Classifier: Topic :: Education
Requires-Python: >=3.7
License-File: LICENSE
Provides-Extra: analysis
Requires-Dist: pandas>=1.3.0; extra == "analysis"
Requires-Dist: matplotlib>=3.3.0; extra == "analysis"
Provides-Extra: search
Requires-Dist: fuzzywuzzy>=0.18.0; extra == "search"
Requires-Dist: python-Levenshtein>=0.12.0; extra == "search"
Provides-Extra: all
Requires-Dist: pandas>=1.3.0; extra == "all"
Requires-Dist: matplotlib>=3.3.0; extra == "all"
Requires-Dist: fuzzywuzzy>=0.18.0; extra == "all"
Requires-Dist: python-Levenshtein>=0.12.0; extra == "all"
Dynamic: author
Dynamic: author-email
Dynamic: classifier
Dynamic: description
Dynamic: description-content-type
Dynamic: home-page
Dynamic: keywords
Dynamic: license
Dynamic: license-file
Dynamic: maintainer
Dynamic: maintainer-email
Dynamic: project-url
Dynamic: provides-extra
Dynamic: requires-python
Dynamic: summary
